[
  {
    "full_name": "Potential17/Zomato-Clone",
    "stargazers_count": 2,
    "open_issues_count": 0,
    "forks_count": 2
  },
  {
    "full_name": "Potential17/Potential17",
    "stargazers_count": 3,
    "open_issues_count": 0,
    "forks_count": 3
  },
  {
    "full_name": "Potential17/Fossee_Screening-Task",
    "stargazers_count": 2,
    "open_issues_count": 0,
    "forks_count": 0
  },
  {
    "full_name": "Potential17/Landing-Page",
    "stargazers_count": 2,
    "open_issues_count": 0,
    "forks_count": 1
  },
  {
    "full_name": "Potential17/Teams-clone",
    "stargazers_count": 2,
    "open_issues_count": 0,
    "forks_count": 2
  },
  {
    "full_name": "Potential17/Onboarding-mockup",
    "stargazers_count": 1,
    "open_issues_count": 0,
    "forks_count": 1
  },
  {
    "full_name": "maintainers/invite-automation",
    "stargazers_count": 213,
    "open_issues_count": 205,
    "forks_count": 2
  },
  {
    "full_name": "Potential17/calci-an",
    "stargazers_count": 2,
    "open_issues_count": 0,
    "forks_count": 1
  },
  {
    "full_name": "Potential17/react-notes-app17",
    "stargazers_count": 2,
    "open_issues_count": 0,
    "forks_count": 1
  },
  {
    "full_name": "Potential17/Rating-Predictor",
    "stargazers_count": 1,
    "open_issues_count": 0,
    "forks_count": 0
  },
  {
    "full_name": "Potential17/web-scraping",
    "stargazers_count": 6,
    "open_issues_count": 19,
    "forks_count": 9
  },
  {
    "full_name": "Potential17/Hacktoberfest-2020",
    "stargazers_count": 41,
    "open_issues_count": 23,
    "forks_count": 129
  }
]